graphPlotPy/__init__.py
graphPlotPy/graphPlotPy.py
graphPlotPy/graphUtils.py
graphPlotPy-0.2.dist-info/METADATA
graphPlotPy-0.2.dist-info/WHEEL
graphPlotPy-0.2.dist-info/top_level.txt
graphPlotPy-0.2.dist-info/RECORD
