Metadata-Version: 2.1
Name: graphPlotPy
Version: 0.2
Summary: A Python package for plotting graphs
Requires-Dist: colorama >=0.4.6
Requires-Dist: colorlog >=6.8.0
Requires-Dist: colormap >=1.0.6
Requires-Dist: contourpy >=1.2.0
Requires-Dist: cycler >=0.12.1
Requires-Dist: easydev >=0.12.1
Requires-Dist: fonttools >=4.47.2
Requires-Dist: kiwisolver >=1.4.5
Requires-Dist: matplotlib >=3.8.2
Requires-Dist: mpmath >=1.3.0
Requires-Dist: numpy >=1.26.3
Requires-Dist: packaging >=23.2
Requires-Dist: pexpect >=4.9.0
Requires-Dist: pillow >=10.2.0
Requires-Dist: ptyprocess >=0.7.0
Requires-Dist: pyparsing >=3.1.1
Requires-Dist: setuptools >=69.0.3
Requires-Dist: six >=1.16.0
Requires-Dist: sympy >=1.12
